admesh/__init__.py
admesh/_base_client.py
admesh/_client.py
admesh/_compat.py
admesh/_constants.py
admesh/_exceptions.py
admesh/_files.py
admesh/_models.py
admesh/_qs.py
admesh/_resource.py
admesh/_response.py
admesh/_streaming.py
admesh/_types.py
admesh/_version.py
admesh/builder.py
admesh/patterns.py
admesh/py.typed
admesh/sanitize_and_build.py
admesh/sanitizer.py
admesh/_utils/__init__.py
admesh/_utils/_logs.py
admesh/_utils/_proxy.py
admesh/_utils/_reflection.py
admesh/_utils/_resources_proxy.py
admesh/_utils/_streams.py
admesh/_utils/_sync.py
admesh/_utils/_transform.py
admesh/_utils/_typing.py
admesh/_utils/_utils.py
admesh/lib/.keep
admesh/resources/__init__.py
admesh/resources/recommend.py
admesh/types/__init__.py
admesh/types/recommend_get_recommendations_params.py
admesh/types/recommend_get_recommendations_response.py
admesh_python-1.2.1.dist-info/METADATA
admesh_python-1.2.1.dist-info/WHEEL
admesh_python-1.2.1.dist-info/licenses/LICENSE
admesh_python-1.2.1.dist-info/RECORD
